isdayoff/__init__.py
isdayoff/isdayoff.py
isdayoff/typingapi.py
isdayoff-1.0.dist-info/LICENSE
isdayoff-1.0.dist-info/METADATA
isdayoff-1.0.dist-info/WHEEL
isdayoff-1.0.dist-info/top_level.txt
isdayoff-1.0.dist-info/RECORD
