Metadata-Version: 2.1
Name: isdayoff
Version: 1.0
Summary: Checking the date for belonging to a non-working day, according to official decrees and orders.
Home-page: https://github.com/kobylinsky-m/isdayoff
Author: Maxim Kobylinsky
Author-email: wg7831@gmail.com
License: MIT
Platform: UNKNOWN
License-File: LICENSE
Requires-Dist: aiohttp (==3.7.4.post0)
Requires-Dist: async-timeout (==3.0.1)
Requires-Dist: attrs (==21.2.0)
Requires-Dist: chardet (==4.0.0)
Requires-Dist: idna (==3.2)
Requires-Dist: idna-ssl (==1.1.0)
Requires-Dist: multidict (==5.1.0)
Requires-Dist: typing-extensions (==3.10.0.0)
Requires-Dist: yarl (==1.6.3)
